rcmf/Chi2_merge.py
rcmf/Corr_Vif.py
rcmf/Cut_Merge.py
rcmf/Data_Distribution.py
rcmf/Data_Explore.py
rcmf/Data_Sampling.py
rcmf/Dummy.py
rcmf/Missing_Data_Impute.py
rcmf/Model_Performance.py
rcmf/PDO_Score.py
rcmf/PSI.py
rcmf/PSR_Crypto.py
rcmf/Woe_Iv.py
rcmf/__init__.py
rcmf-1.0.6.dist-info/METADATA
rcmf-1.0.6.dist-info/RECORD
rcmf-1.0.6.dist-info/WHEEL
rcmf-1.0.6.dist-info/top_level.txt
