Metadata-Version: 2.1
Name: rcmf
Version: 1.0.6
Summary: A risk control modeling toolbox, include scattered function for building scorecard/machine learn model.
Home-page: UNKNOWN
Author: Tigflanker & deng@jd partners
Author-email: tigflanker@qq.com
License: UNKNOWN
Keywords: scorecard,python,toolbox
Platform: UNKNOWN
Classifier: Development Status :: 4 - Beta
Classifier: Intended Audience :: Developers
Classifier: License :: OSI Approved :: MIT License
Classifier: Programming Language :: Python :: 3
Classifier: Programming Language :: Python :: 3.4
Classifier: Programming Language :: Python :: 3.5
Classifier: Programming Language :: Python :: 3.6
Classifier: Programming Language :: Python :: 3.7
Requires-Dist: numpy
Requires-Dist: pandas
Requires-Dist: scipy
Requires-Dist: matplotlib
Requires-Dist: seaborn
Requires-Dist: sklearn
Requires-Dist: scikit-plot
Requires-Dist: statsmodels
